{"v":4,"entries":{"components-badge--docs":{"id":"components-badge--docs","title":"Components/Badge","name":"Docs","importPath":"./src/stories/Badge.stories.tsx","type":"docs","tags":["autodocs","play-fn","docs"],"storiesImports":[]},"components-badge--primary":{"type":"story","id":"components-badge--primary","name":"Primary","title":"Components/Badge","importPath":"./src/stories/Badge.stories.tsx","tags":["autodocs","play-fn","story"]},"components-badge--secondary":{"type":"story","id":"components-badge--secondary","name":"Secondary","title":"Components/Badge","importPath":"./src/stories/Badge.stories.tsx","tags":["autodocs","play-fn","story"]},"components-badge--success":{"type":"story","id":"components-badge--success","name":"Success","title":"Components/Badge","importPath":"./src/stories/Badge.stories.tsx","tags":["autodocs","play-fn","story"]},"components-badge--warning":{"type":"story","id":"components-badge--warning","name":"Warning","title":"Components/Badge","importPath":"./src/stories/Badge.stories.tsx","tags":["autodocs","play-fn","story"]},"components-badge--error":{"type":"story","id":"components-badge--error","name":"Error","title":"Components/Badge","importPath":"./src/stories/Badge.stories.tsx","tags":["autodocs","play-fn","story"]},"components-badge--info":{"type":"story","id":"components-badge--info","name":"Info","title":"Components/Badge","importPath":"./src/stories/Badge.stories.tsx","tags":["autodocs","play-fn","story"]},"components-badge--small":{"type":"story","id":"components-badge--small","name":"Small","title":"Components/Badge","importPath":"./src/stories/Badge.stories.tsx","tags":["autodocs","play-fn","story"]},"components-badge--large":{"type":"story","id":"components-badge--large","name":"Large","title":"Components/Badge","importPath":"./src/stories/Badge.stories.tsx","tags":["autodocs","play-fn","story"]},"components-badge--rounded":{"type":"story","id":"components-badge--rounded","name":"Rounded","title":"Components/Badge","importPath":"./src/stories/Badge.stories.tsx","tags":["autodocs","play-fn","story"]},"components-badge--with-dot":{"type":"story","id":"components-badge--with-dot","name":"With Dot","title":"Components/Badge","importPath":"./src/stories/Badge.stories.tsx","tags":["autodocs","play-fn","story"]},"components-badge--with-custom-class":{"type":"story","id":"components-badge--with-custom-class","name":"With Custom Class","title":"Components/Badge","importPath":"./src/stories/Badge.stories.tsx","tags":["autodocs","play-fn","story"]},"components-button--docs":{"id":"components-button--docs","title":"Components/Button","name":"Docs","importPath":"./src/stories/Button.stories.tsx","type":"docs","tags":["autodocs","play-fn","docs"],"storiesImports":[]},"components-button--primary":{"type":"story","id":"components-button--primary","name":"Primary","title":"Components/Button","importPath":"./src/stories/Button.stories.tsx","tags":["autodocs","play-fn","story"]},"components-button--secondary":{"type":"story","id":"components-button--secondary","name":"Secondary","title":"Components/Button","importPath":"./src/stories/Button.stories.tsx","tags":["autodocs","play-fn","story"]},"components-button--outline":{"type":"story","id":"components-button--outline","name":"Outline","title":"Components/Button","importPath":"./src/stories/Button.stories.tsx","tags":["autodocs","play-fn","story"]},"components-button--ghost":{"type":"story","id":"components-button--ghost","name":"Ghost","title":"Components/Button","importPath":"./src/stories/Button.stories.tsx","tags":["autodocs","play-fn","story"]},"components-button--danger":{"type":"story","id":"components-button--danger","name":"Danger","title":"Components/Button","importPath":"./src/stories/Button.stories.tsx","tags":["autodocs","play-fn","story"]},"components-button--small":{"type":"story","id":"components-button--small","name":"Small","title":"Components/Button","importPath":"./src/stories/Button.stories.tsx","tags":["autodocs","play-fn","story"]},"components-button--medium":{"type":"story","id":"components-button--medium","name":"Medium","title":"Components/Button","importPath":"./src/stories/Button.stories.tsx","tags":["autodocs","play-fn","story"]},"components-button--large":{"type":"story","id":"components-button--large","name":"Large","title":"Components/Button","importPath":"./src/stories/Button.stories.tsx","tags":["autodocs","play-fn","story"]},"components-button--disabled":{"type":"story","id":"components-button--disabled","name":"Disabled","title":"Components/Button","importPath":"./src/stories/Button.stories.tsx","tags":["autodocs","play-fn","story"]},"components-button--loading":{"type":"story","id":"components-button--loading","name":"Loading","title":"Components/Button","importPath":"./src/stories/Button.stories.tsx","tags":["autodocs","play-fn","story"]},"components-button--full-width":{"type":"story","id":"components-button--full-width","name":"Full Width","title":"Components/Button","importPath":"./src/stories/Button.stories.tsx","tags":["autodocs","play-fn","story"]},"components-card--docs":{"id":"components-card--docs","title":"Components/Card","name":"Docs","importPath":"./src/stories/Card.stories.tsx","type":"docs","tags":["autodocs","play-fn","docs"],"storiesImports":[]},"components-card--default":{"type":"story","id":"components-card--default","name":"Default","title":"Components/Card","importPath":"./src/stories/Card.stories.tsx","tags":["autodocs","play-fn","story"]},"components-card--outlined":{"type":"story","id":"components-card--outlined","name":"Outlined","title":"Components/Card","importPath":"./src/stories/Card.stories.tsx","tags":["autodocs","play-fn","story"]},"components-card--elevated":{"type":"story","id":"components-card--elevated","name":"Elevated","title":"Components/Card","importPath":"./src/stories/Card.stories.tsx","tags":["autodocs","play-fn","story"]},"components-card--small-padding":{"type":"story","id":"components-card--small-padding","name":"Small Padding","title":"Components/Card","importPath":"./src/stories/Card.stories.tsx","tags":["autodocs","play-fn","story"]},"components-card--large-padding":{"type":"story","id":"components-card--large-padding","name":"Large Padding","title":"Components/Card","importPath":"./src/stories/Card.stories.tsx","tags":["autodocs","play-fn","story"]},"components-card--with-header":{"type":"story","id":"components-card--with-header","name":"With Header","title":"Components/Card","importPath":"./src/stories/Card.stories.tsx","tags":["autodocs","play-fn","story"]},"components-card--with-footer":{"type":"story","id":"components-card--with-footer","name":"With Footer","title":"Components/Card","importPath":"./src/stories/Card.stories.tsx","tags":["autodocs","play-fn","story"]},"components-card--hoverable":{"type":"story","id":"components-card--hoverable","name":"Hoverable","title":"Components/Card","importPath":"./src/stories/Card.stories.tsx","tags":["autodocs","play-fn","story"]},"components-card--complex-content":{"type":"story","id":"components-card--complex-content","name":"Complex Content","title":"Components/Card","importPath":"./src/stories/Card.stories.tsx","tags":["autodocs","play-fn","story"]},"components-errorboundary--docs":{"id":"components-errorboundary--docs","title":"Components/ErrorBoundary","name":"Docs","importPath":"./src/stories/ErrorBoundary.stories.tsx","type":"docs","tags":["autodocs","play-fn","docs"],"storiesImports":[]},"components-errorboundary--default":{"type":"story","id":"components-errorboundary--default","name":"Default","title":"Components/ErrorBoundary","importPath":"./src/stories/ErrorBoundary.stories.tsx","tags":["autodocs","play-fn","story"]},"components-errorboundary--with-error":{"type":"story","id":"components-errorboundary--with-error","name":"With Error","title":"Components/ErrorBoundary","importPath":"./src/stories/ErrorBoundary.stories.tsx","tags":["autodocs","play-fn","story"]},"components-errorboundary--with-custom-fallback":{"type":"story","id":"components-errorboundary--with-custom-fallback","name":"With Custom Fallback","title":"Components/ErrorBoundary","importPath":"./src/stories/ErrorBoundary.stories.tsx","tags":["autodocs","play-fn","story"]},"components-errorboundary--with-component-error":{"type":"story","id":"components-errorboundary--with-component-error","name":"With Component Error","title":"Components/ErrorBoundary","importPath":"./src/stories/ErrorBoundary.stories.tsx","tags":["autodocs","play-fn","story"]},"components-errorboundary--with-nested-content":{"type":"story","id":"components-errorboundary--with-nested-content","name":"With Nested Content","title":"Components/ErrorBoundary","importPath":"./src/stories/ErrorBoundary.stories.tsx","tags":["autodocs","story"]},"components-input--docs":{"id":"components-input--docs","title":"Components/Input","name":"Docs","importPath":"./src/stories/Input.stories.tsx","type":"docs","tags":["autodocs","play-fn","docs"],"storiesImports":[]},"components-input--default":{"type":"story","id":"components-input--default","name":"Default","title":"Components/Input","importPath":"./src/stories/Input.stories.tsx","tags":["autodocs","play-fn","story"]},"components-input--filled":{"type":"story","id":"components-input--filled","name":"Filled","title":"Components/Input","importPath":"./src/stories/Input.stories.tsx","tags":["autodocs","play-fn","story"]},"components-input--outlined":{"type":"story","id":"components-input--outlined","name":"Outlined","title":"Components/Input","importPath":"./src/stories/Input.stories.tsx","tags":["autodocs","play-fn","story"]},"components-input--small":{"type":"story","id":"components-input--small","name":"Small","title":"Components/Input","importPath":"./src/stories/Input.stories.tsx","tags":["autodocs","play-fn","story"]},"components-input--large":{"type":"story","id":"components-input--large","name":"Large","title":"Components/Input","importPath":"./src/stories/Input.stories.tsx","tags":["autodocs","play-fn","story"]},"components-input--with-error":{"type":"story","id":"components-input--with-error","name":"With Error","title":"Components/Input","importPath":"./src/stories/Input.stories.tsx","tags":["autodocs","play-fn","story"]},"components-input--with-helper-text":{"type":"story","id":"components-input--with-helper-text","name":"With Helper Text","title":"Components/Input","importPath":"./src/stories/Input.stories.tsx","tags":["autodocs","play-fn","story"]},"components-input--with-start-icon":{"type":"story","id":"components-input--with-start-icon","name":"With Start Icon","title":"Components/Input","importPath":"./src/stories/Input.stories.tsx","tags":["autodocs","play-fn","story"]},"components-input--with-end-icon":{"type":"story","id":"components-input--with-end-icon","name":"With End Icon","title":"Components/Input","importPath":"./src/stories/Input.stories.tsx","tags":["autodocs","play-fn","story"]},"components-input--disabled":{"type":"story","id":"components-input--disabled","name":"Disabled","title":"Components/Input","importPath":"./src/stories/Input.stories.tsx","tags":["autodocs","play-fn","story"]},"components-input--full-width":{"type":"story","id":"components-input--full-width","name":"Full Width","title":"Components/Input","importPath":"./src/stories/Input.stories.tsx","tags":["autodocs","play-fn","story"]},"charts-linechart--docs":{"id":"charts-linechart--docs","title":"Charts/LineChart","name":"Docs","importPath":"./src/stories/LineChart.stories.tsx","type":"docs","tags":["autodocs","play-fn","docs"],"storiesImports":[]},"charts-linechart--default":{"type":"story","id":"charts-linechart--default","name":"Default","title":"Charts/LineChart","importPath":"./src/stories/LineChart.stories.tsx","tags":["autodocs","play-fn","story"]},"charts-linechart--custom-size":{"type":"story","id":"charts-linechart--custom-size","name":"Custom Size","title":"Charts/LineChart","importPath":"./src/stories/LineChart.stories.tsx","tags":["autodocs","play-fn","story"]},"charts-linechart--custom-styles":{"type":"story","id":"charts-linechart--custom-styles","name":"Custom Styles","title":"Charts/LineChart","importPath":"./src/stories/LineChart.stories.tsx","tags":["autodocs","play-fn","story"]},"charts-linechart--custom-formatters":{"type":"story","id":"charts-linechart--custom-formatters","name":"Custom Formatters","title":"Charts/LineChart","importPath":"./src/stories/LineChart.stories.tsx","tags":["autodocs","play-fn","story"]},"charts-linechart--with-tooltip":{"type":"story","id":"charts-linechart--with-tooltip","name":"With Tooltip","title":"Charts/LineChart","importPath":"./src/stories/LineChart.stories.tsx","tags":["autodocs","play-fn","story"]},"charts-linechart--empty-data":{"type":"story","id":"charts-linechart--empty-data","name":"Empty Data","title":"Charts/LineChart","importPath":"./src/stories/LineChart.stories.tsx","tags":["autodocs","play-fn","story"]},"charts-linechart--single-data-point":{"type":"story","id":"charts-linechart--single-data-point","name":"Single Data Point","title":"Charts/LineChart","importPath":"./src/stories/LineChart.stories.tsx","tags":["autodocs","play-fn","story"]},"charts-linechart--large-data-set":{"type":"story","id":"charts-linechart--large-data-set","name":"Large Data Set","title":"Charts/LineChart","importPath":"./src/stories/LineChart.stories.tsx","tags":["autodocs","play-fn","story"]},"charts-linechart--accessible-chart":{"type":"story","id":"charts-linechart--accessible-chart","name":"Accessible Chart","title":"Charts/LineChart","importPath":"./src/stories/LineChart.stories.tsx","tags":["autodocs","play-fn","story"]},"components-loadingskeleton--docs":{"id":"components-loadingskeleton--docs","title":"Components/LoadingSkeleton","name":"Docs","importPath":"./src/stories/LoadingSkeleton.stories.tsx","type":"docs","tags":["autodocs","play-fn","docs"],"storiesImports":[]},"components-loadingskeleton--default":{"type":"story","id":"components-loadingskeleton--default","name":"Default","title":"Components/LoadingSkeleton","importPath":"./src/stories/LoadingSkeleton.stories.tsx","tags":["autodocs","play-fn","story"]},"components-loadingskeleton--circle":{"type":"story","id":"components-loadingskeleton--circle","name":"Circle","title":"Components/LoadingSkeleton","importPath":"./src/stories/LoadingSkeleton.stories.tsx","tags":["autodocs","play-fn","story"]},"components-loadingskeleton--text":{"type":"story","id":"components-loadingskeleton--text","name":"Text","title":"Components/LoadingSkeleton","importPath":"./src/stories/LoadingSkeleton.stories.tsx","tags":["autodocs","play-fn","story"]},"components-loadingskeleton--multiple-lines":{"type":"story","id":"components-loadingskeleton--multiple-lines","name":"Multiple Lines","title":"Components/LoadingSkeleton","importPath":"./src/stories/LoadingSkeleton.stories.tsx","tags":["autodocs","play-fn","story"]},"components-loadingskeleton--with-custom-class":{"type":"story","id":"components-loadingskeleton--with-custom-class","name":"With Custom Class","title":"Components/LoadingSkeleton","importPath":"./src/stories/LoadingSkeleton.stories.tsx","tags":["autodocs","play-fn","story"]},"components-loadingspinner--docs":{"id":"components-loadingspinner--docs","title":"Components/LoadingSpinner","name":"Docs","importPath":"./src/stories/LoadingSpinner.stories.tsx","type":"docs","tags":["autodocs","play-fn","docs"],"storiesImports":[]},"components-loadingspinner--default":{"type":"story","id":"components-loadingspinner--default","name":"Default","title":"Components/LoadingSpinner","importPath":"./src/stories/LoadingSpinner.stories.tsx","tags":["autodocs","play-fn","story"]},"components-loadingspinner--small":{"type":"story","id":"components-loadingspinner--small","name":"Small","title":"Components/LoadingSpinner","importPath":"./src/stories/LoadingSpinner.stories.tsx","tags":["autodocs","play-fn","story"]},"components-loadingspinner--large":{"type":"story","id":"components-loadingspinner--large","name":"Large","title":"Components/LoadingSpinner","importPath":"./src/stories/LoadingSpinner.stories.tsx","tags":["autodocs","play-fn","story"]},"components-loadingspinner--custom-label":{"type":"story","id":"components-loadingspinner--custom-label","name":"Custom Label","title":"Components/LoadingSpinner","importPath":"./src/stories/LoadingSpinner.stories.tsx","tags":["autodocs","play-fn","story"]},"components-loadingspinner--with-custom-class":{"type":"story","id":"components-loadingspinner--with-custom-class","name":"With Custom Class","title":"Components/LoadingSpinner","importPath":"./src/stories/LoadingSpinner.stories.tsx","tags":["autodocs","play-fn","story"]},"metrics-metricscard--docs":{"id":"metrics-metricscard--docs","title":"Metrics/MetricsCard","name":"Docs","importPath":"./src/stories/MetricsCard.stories.tsx","type":"docs","tags":["autodocs","play-fn","docs"],"storiesImports":[]},"metrics-metricscard--default":{"type":"story","id":"metrics-metricscard--default","name":"Default","title":"Metrics/MetricsCard","importPath":"./src/stories/MetricsCard.stories.tsx","tags":["autodocs","play-fn","story"]},"metrics-metricscard--loading":{"type":"story","id":"metrics-metricscard--loading","name":"Loading","title":"Metrics/MetricsCard","importPath":"./src/stories/MetricsCard.stories.tsx","tags":["autodocs","play-fn","story"]},"metrics-metricscard--error":{"type":"story","id":"metrics-metricscard--error","name":"Error","title":"Metrics/MetricsCard","importPath":"./src/stories/MetricsCard.stories.tsx","tags":["autodocs","play-fn","story"]},"metrics-metricscard--with-tooltip":{"type":"story","id":"metrics-metricscard--with-tooltip","name":"With Tooltip","title":"Metrics/MetricsCard","importPath":"./src/stories/MetricsCard.stories.tsx","tags":["autodocs","play-fn","story"]},"metrics-metricscard--negative-trend":{"type":"story","id":"metrics-metricscard--negative-trend","name":"Negative Trend","title":"Metrics/MetricsCard","importPath":"./src/stories/MetricsCard.stories.tsx","tags":["autodocs","play-fn","story"]},"metrics-metricscard--custom-formatters":{"type":"story","id":"metrics-metricscard--custom-formatters","name":"Custom Formatters","title":"Metrics/MetricsCard","importPath":"./src/stories/MetricsCard.stories.tsx","tags":["autodocs","play-fn","story"]},"metrics-metricscard--clickable":{"type":"story","id":"metrics-metricscard--clickable","name":"Clickable","title":"Metrics/MetricsCard","importPath":"./src/stories/MetricsCard.stories.tsx","tags":["autodocs","play-fn","story"]},"metrics-metricscard--custom-styles":{"type":"story","id":"metrics-metricscard--custom-styles","name":"Custom Styles","title":"Metrics/MetricsCard","importPath":"./src/stories/MetricsCard.stories.tsx","tags":["autodocs","play-fn","story"]},"components-modal--docs":{"id":"components-modal--docs","title":"Components/Modal","name":"Docs","importPath":"./src/stories/Modal.stories.tsx","type":"docs","tags":["autodocs","docs"],"storiesImports":[]},"components-modal--default":{"type":"story","id":"components-modal--default","name":"Default","title":"Components/Modal","importPath":"./src/stories/Modal.stories.tsx","tags":["autodocs","story"]},"components-modal--with-title":{"type":"story","id":"components-modal--with-title","name":"With Title","title":"Components/Modal","importPath":"./src/stories/Modal.stories.tsx","tags":["autodocs","story"]},"components-modal--small-size":{"type":"story","id":"components-modal--small-size","name":"Small Size","title":"Components/Modal","importPath":"./src/stories/Modal.stories.tsx","tags":["autodocs","story"]},"components-modal--large-size":{"type":"story","id":"components-modal--large-size","name":"Large Size","title":"Components/Modal","importPath":"./src/stories/Modal.stories.tsx","tags":["autodocs","story"]},"components-modal--with-close-button":{"type":"story","id":"components-modal--with-close-button","name":"With Close Button","title":"Components/Modal","importPath":"./src/stories/Modal.stories.tsx","tags":["autodocs","story"]},"components-modal--with-long-content":{"type":"story","id":"components-modal--with-long-content","name":"With Long Content","title":"Components/Modal","importPath":"./src/stories/Modal.stories.tsx","tags":["autodocs","story"]},"components-progress--docs":{"id":"components-progress--docs","title":"Components/Progress","name":"Docs","importPath":"./src/stories/Progress.stories.tsx","type":"docs","tags":["autodocs","play-fn","docs"],"storiesImports":[]},"components-progress--default":{"type":"story","id":"components-progress--default","name":"Default","title":"Components/Progress","importPath":"./src/stories/Progress.stories.tsx","tags":["autodocs","play-fn","story"]},"components-progress--success":{"type":"story","id":"components-progress--success","name":"Success","title":"Components/Progress","importPath":"./src/stories/Progress.stories.tsx","tags":["autodocs","play-fn","story"]},"components-progress--warning":{"type":"story","id":"components-progress--warning","name":"Warning","title":"Components/Progress","importPath":"./src/stories/Progress.stories.tsx","tags":["autodocs","play-fn","story"]},"components-progress--danger":{"type":"story","id":"components-progress--danger","name":"Danger","title":"Components/Progress","importPath":"./src/stories/Progress.stories.tsx","tags":["autodocs","play-fn","story"]},"components-progress--small":{"type":"story","id":"components-progress--small","name":"Small","title":"Components/Progress","importPath":"./src/stories/Progress.stories.tsx","tags":["autodocs","play-fn","story"]},"components-progress--large":{"type":"story","id":"components-progress--large","name":"Large","title":"Components/Progress","importPath":"./src/stories/Progress.stories.tsx","tags":["autodocs","play-fn","story"]},"components-progress--with-label":{"type":"story","id":"components-progress--with-label","name":"With Label","title":"Components/Progress","importPath":"./src/stories/Progress.stories.tsx","tags":["autodocs","play-fn","story"]},"components-progress--with-value-outside":{"type":"story","id":"components-progress--with-value-outside","name":"With Value Outside","title":"Components/Progress","importPath":"./src/stories/Progress.stories.tsx","tags":["autodocs","play-fn","story"]},"components-progress--with-value-inside":{"type":"story","id":"components-progress--with-value-inside","name":"With Value Inside","title":"Components/Progress","importPath":"./src/stories/Progress.stories.tsx","tags":["autodocs","play-fn","story"]},"components-progress--striped":{"type":"story","id":"components-progress--striped","name":"Striped","title":"Components/Progress","importPath":"./src/stories/Progress.stories.tsx","tags":["autodocs","play-fn","story"]},"components-progress--animated":{"type":"story","id":"components-progress--animated","name":"Animated","title":"Components/Progress","importPath":"./src/stories/Progress.stories.tsx","tags":["autodocs","play-fn","story"]},"components-progress--complete-progress":{"type":"story","id":"components-progress--complete-progress","name":"Complete Progress","title":"Components/Progress","importPath":"./src/stories/Progress.stories.tsx","tags":["autodocs","play-fn","story"]},"components-switch--docs":{"id":"components-switch--docs","title":"Components/Switch","name":"Docs","importPath":"./src/stories/Switch.stories.tsx","type":"docs","tags":["autodocs","play-fn","docs"],"storiesImports":[]},"components-switch--default":{"type":"story","id":"components-switch--default","name":"Default","title":"Components/Switch","importPath":"./src/stories/Switch.stories.tsx","tags":["autodocs","play-fn","story"]},"components-switch--success":{"type":"story","id":"components-switch--success","name":"Success","title":"Components/Switch","importPath":"./src/stories/Switch.stories.tsx","tags":["autodocs","play-fn","story"]},"components-switch--danger":{"type":"story","id":"components-switch--danger","name":"Danger","title":"Components/Switch","importPath":"./src/stories/Switch.stories.tsx","tags":["autodocs","play-fn","story"]},"components-switch--small":{"type":"story","id":"components-switch--small","name":"Small","title":"Components/Switch","importPath":"./src/stories/Switch.stories.tsx","tags":["autodocs","play-fn","story"]},"components-switch--large":{"type":"story","id":"components-switch--large","name":"Large","title":"Components/Switch","importPath":"./src/stories/Switch.stories.tsx","tags":["autodocs","play-fn","story"]},"components-switch--with-label":{"type":"story","id":"components-switch--with-label","name":"With Label","title":"Components/Switch","importPath":"./src/stories/Switch.stories.tsx","tags":["autodocs","play-fn","story"]},"components-switch--with-description":{"type":"story","id":"components-switch--with-description","name":"With Description","title":"Components/Switch","importPath":"./src/stories/Switch.stories.tsx","tags":["autodocs","play-fn","story"]},"components-switch--disabled":{"type":"story","id":"components-switch--disabled","name":"Disabled","title":"Components/Switch","importPath":"./src/stories/Switch.stories.tsx","tags":["autodocs","play-fn","story"]},"components-switch--checked":{"type":"story","id":"components-switch--checked","name":"Checked","title":"Components/Switch","importPath":"./src/stories/Switch.stories.tsx","tags":["autodocs","play-fn","story"]},"components-switch--interactive":{"type":"story","id":"components-switch--interactive","name":"Interactive","title":"Components/Switch","importPath":"./src/stories/Switch.stories.tsx","tags":["autodocs","play-fn","story"]},"components-toast--docs":{"id":"components-toast--docs","title":"Components/Toast","name":"Docs","importPath":"./src/stories/Toast.stories.tsx","type":"docs","tags":["autodocs","play-fn","docs"],"storiesImports":[]},"components-toast--info":{"type":"story","id":"components-toast--info","name":"Info","title":"Components/Toast","importPath":"./src/stories/Toast.stories.tsx","tags":["autodocs","play-fn","story"]},"components-toast--success":{"type":"story","id":"components-toast--success","name":"Success","title":"Components/Toast","importPath":"./src/stories/Toast.stories.tsx","tags":["autodocs","play-fn","story"]},"components-toast--warning":{"type":"story","id":"components-toast--warning","name":"Warning","title":"Components/Toast","importPath":"./src/stories/Toast.stories.tsx","tags":["autodocs","play-fn","story"]},"components-toast--error":{"type":"story","id":"components-toast--error","name":"Error","title":"Components/Toast","importPath":"./src/stories/Toast.stories.tsx","tags":["autodocs","play-fn","story"]},"components-toast--with-action":{"type":"story","id":"components-toast--with-action","name":"With Action","title":"Components/Toast","importPath":"./src/stories/Toast.stories.tsx","tags":["autodocs","play-fn","story"]},"components-toast--with-close-button":{"type":"story","id":"components-toast--with-close-button","name":"With Close Button","title":"Components/Toast","importPath":"./src/stories/Toast.stories.tsx","tags":["autodocs","play-fn","story"]},"components-toast--top-left":{"type":"story","id":"components-toast--top-left","name":"Top Left","title":"Components/Toast","importPath":"./src/stories/Toast.stories.tsx","tags":["autodocs","play-fn","story"]},"components-toast--auto-closing":{"type":"story","id":"components-toast--auto-closing","name":"Auto Closing","title":"Components/Toast","importPath":"./src/stories/Toast.stories.tsx","tags":["autodocs","play-fn","story"]},"components-toast--complex-toast":{"type":"story","id":"components-toast--complex-toast","name":"Complex Toast","title":"Components/Toast","importPath":"./src/stories/Toast.stories.tsx","tags":["autodocs","play-fn","story"]}}}
